numpy_dataframe/__init__.py
numpy_dataframe/numpy_dataframe.py
numpy_dataframe/numpy_dataframe_unknown_mod.py
numpy_dataframe-0.1.7.dist-info/LICENSE
numpy_dataframe-0.1.7.dist-info/METADATA
numpy_dataframe-0.1.7.dist-info/WHEEL
numpy_dataframe-0.1.7.dist-info/top_level.txt
numpy_dataframe-0.1.7.dist-info/RECORD
