Metadata-Version: 2.1
Name: numpy-dataframe
Version: 0.1.7
Summary: A simple dataframe implementation using numpy as its basic element
Home-page: UNKNOWN
Author: Carlos Molinero
Author-email: 
License: MIT
Platform: UNKNOWN
License-File: LICENSE
